{"name":"aydin","male":[{"y":2004,"r":878,"c":197},{"y":2005,"r":850,"c":216},{"y":2006,"r":737,"c":289},{"y":2007,"r":712,"c":325},{"y":2008,"r":629,"c":393},{"y":2009,"r":645,"c":384},{"y":2010,"r":670,"c":358},{"y":2011,"r":655,"c":358},{"y":2012,"r":713,"c":332},{"y":2013,"r":707,"c":332},{"y":2014,"r":741,"c":321},{"y":2015,"r":802,"c":288},{"y":2016,"r":818,"c":280},{"y":2017,"r":855,"c":255},{"y":2018,"r":863,"c":254},{"y":2019,"r":826,"c":273},{"y":2020,"r":869,"c":259},{"y":2021,"r":897,"c":256}],"female":[]}