{"name":"chesley","male":[{"y":1880,"r":937,"c":5},{"y":1881,"r":721,"c":7},{"y":1882,"r":857,"c":6},{"y":1884,"r":873,"c":6},{"y":1885,"r":849,"c":6},{"y":1886,"r":858,"c":6},{"y":1889,"r":994,"c":5},{"y":1890,"r":822,"c":7},{"y":1891,"r":865,"c":6},{"y":1894,"r":636,"c":11},{"y":1896,"r":839,"c":8},{"y":1897,"r":799,"c":8},{"y":1898,"r":752,"c":9},{"y":1899,"r":873,"c":7},{"y":1901,"r":871,"c":7},{"y":1902,"r":755,"c":10},{"y":1903,"r":924,"c":7},{"y":1905,"r":848,"c":9},{"y":1907,"r":939,"c":9},{"y":1910,"r":938,"c":12}],"female":[]}