{"name":"cristobal","male":[{"y":1975,"r":955,"c":74},{"y":1979,"r":956,"c":86},{"y":1980,"r":997,"c":82},{"y":1981,"r":916,"c":96},{"y":1982,"r":872,"c":104},{"y":1983,"r":897,"c":96},{"y":1984,"r":969,"c":84},{"y":1985,"r":999,"c":83},{"y":1989,"r":985,"c":107},{"y":1990,"r":924,"c":125},{"y":1991,"r":987,"c":118},{"y":1993,"r":905,"c":141},{"y":1994,"r":910,"c":144},{"y":1995,"r":914,"c":147},{"y":1996,"r":952,"c":136},{"y":1997,"r":920,"c":148},{"y":1999,"r":978,"c":146},{"y":2000,"r":813,"c":198},{"y":2001,"r":708,"c":249},{"y":2002,"r":989,"c":159},{"y":2003,"r":934,"c":176},{"y":2005,"r":988,"c":175},{"y":2007,"r":919,"c":215}],"female":[]}