{"name":"malvin","male":[{"y":1886,"r":923,"c":6},{"y":1906,"r":893,"c":9},{"y":1912,"r":983,"c":22},{"y":1913,"r":742,"c":40},{"y":1915,"r":888,"c":49},{"y":1917,"r":976,"c":45},{"y":1919,"r":954,"c":50},{"y":1920,"r":873,"c":62},{"y":1921,"r":840,"c":68},{"y":1922,"r":910,"c":59},{"y":1924,"r":877,"c":62},{"y":1925,"r":907,"c":56},{"y":1927,"r":895,"c":58},{"y":1928,"r":934,"c":53},{"y":1929,"r":979,"c":48},{"y":1930,"r":852,"c":60},{"y":1934,"r":914,"c":48},{"y":1935,"r":920,"c":48}],"female":[]}