{"name":"mariano","male":[{"y":1907,"r":974,"c":9},{"y":1909,"r":825,"c":13},{"y":1910,"r":912,"c":13},{"y":1911,"r":883,"c":15},{"y":1912,"r":733,"c":35},{"y":1914,"r":876,"c":39},{"y":1916,"r":909,"c":49},{"y":1919,"r":924,"c":53},{"y":1920,"r":927,"c":56},{"y":1921,"r":881,"c":63},{"y":1922,"r":937,"c":56},{"y":1923,"r":909,"c":57},{"y":1924,"r":878,"c":62},{"y":1925,"r":929,"c":53},{"y":1926,"r":868,"c":60},{"y":1927,"r":970,"c":52},{"y":1928,"r":832,"c":63},{"y":1930,"r":883,"c":57},{"y":1931,"r":873,"c":54},{"y":1932,"r":871,"c":54},{"y":1937,"r":952,"c":44},{"y":1938,"r":935,"c":46},{"y":1953,"r":952,"c":57},{"y":1954,"r":988,"c":57},{"y":1958,"r":966,"c":62},{"y":1961,"r":929,"c":68},{"y":1963,"r":959,"c":62},{"y":1967,"r":953,"c":58},{"y":1968,"r":981,"c":57},{"y":1971,"r":961,"c":72},{"y":1972,"r":965,"c":71},{"y":1973,"r":953,"c":72},{"y":1974,"r":933,"c":77},{"y":1975,"r":958,"c":74},{"y":1976,"r":886,"c":88},{"y":1977,"r":967,"c":79},{"y":1979,"r":943,"c":88},{"y":1983,"r":939,"c":89},{"y":1987,"r":986,"c":93},{"y":1988,"r":986,"c":97},{"y":1993,"r":917,"c":138},{"y":1998,"r":997,"c":138},{"y":1999,"r":841,"c":180},{"y":2000,"r":921,"c":167},{"y":2001,"r":931,"c":167},{"y":2005,"r":963,"c":182},{"y":2007,"r":929,"c":214},{"y":2011,"r":955,"c":208}],"female":[]}