{"name":"raheem","male":[{"y":1975,"r":992,"c":69},{"y":1977,"r":699,"c":148},{"y":1978,"r":825,"c":108},{"y":1979,"r":809,"c":117},{"y":1980,"r":698,"c":156},{"y":1981,"r":700,"c":154},{"y":1982,"r":781,"c":127},{"y":1983,"r":799,"c":121},{"y":1984,"r":982,"c":83},{"y":1985,"r":969,"c":89},{"y":1987,"r":887,"c":112},{"y":1988,"r":940,"c":105},{"y":1989,"r":798,"c":156},{"y":1990,"r":772,"c":174},{"y":1991,"r":688,"c":217},{"y":1992,"r":509,"c":395},{"y":1993,"r":417,"c":556},{"y":1994,"r":515,"c":384},{"y":1995,"r":571,"c":321},{"y":1996,"r":625,"c":278},{"y":1997,"r":710,"c":223},{"y":1998,"r":737,"c":221},{"y":1999,"r":830,"c":183},{"y":2000,"r":916,"c":169}],"female":[]}